MANIFEST.in
README.rst
setup.py
collective/__init__.py
collective.cachepurger.egg-info/PKG-INFO
collective.cachepurger.egg-info/SOURCES.txt
collective.cachepurger.egg-info/dependency_links.txt
collective.cachepurger.egg-info/entry_points.txt
collective.cachepurger.egg-info/namespace_packages.txt
collective.cachepurger.egg-info/not-zip-safe
collective.cachepurger.egg-info/requires.txt
collective.cachepurger.egg-info/top_level.txt
collective/cachepurger/README.txt
collective/cachepurger/__init__.py
collective/cachepurger/configure.zcml
collective/cachepurger/purger.py
docs/HISTORY.txt