Metadata-Version: 1.1
Name: collective.cachepurger
Version: 1.1
Summary: Purges RAM caches and refreshes resource registry
Home-page: https://github.com/headnet/collective.cachepurger
Author: Anton Stonor
Author-email: anton@headnet.dk
License: GPL
Platform: UNKNOWN
Classifier: Programming Language :: Python
